README
setup.cfg
setup.py
wuml/DManager.py
wuml/IKDR.py
wuml/IO.py
wuml/L2X.py
wuml/__init__.py
wuml/autoencoder.py
wuml/basicNetwork.py
wuml/classification.py
wuml/cluster.py
wuml/combinedNetwork.py
wuml/data_stats.py
wuml/dates_and_time.py
wuml/dependency.py
wuml/dimension_reduction.py
wuml/distance_between_distributions.py
wuml/distributions.py
wuml/explainer.py
wuml/feature_selection.py
wuml/flow.py
wuml/generate_data.py
wuml/gumbel.py
wuml/gumbel_softmax.py
wuml/hyperparameter_tuning.py
wuml/imputation.py
wuml/kde.py
wuml/kernelShap.py
wuml/kernels.py
wuml/matrix_manipulate.py
wuml/measure.py
wuml/operations.py
wuml/opt_gaussian.py
wuml/preprocess.py
wuml/random_features.py
wuml/rebalance_data.py
wuml/regression.py
wuml/run_k_fold_on_function.py
wuml/sampling.py
wuml/string_manipulate.py
wuml/synthetic_data.py
wuml/system.py
wuml/torch_functions.py
wuml/type_check.py
wuml/wData.py
wuml.egg-info/PKG-INFO
wuml.egg-info/SOURCES.txt
wuml.egg-info/dependency_links.txt
wuml.egg-info/requires.txt
wuml.egg-info/top_level.txt