Metadata-Version: 2.1
Name: wuml
Version: 0.148
Summary: A library that simplifies some basic ML stuff.
Home-page: https://github.com/endsley/wuML.git
Download-URL: https://github.com/endsley/wuML/archive/refs/tags/0.148.tar.gz
Author: Chieh Wu
Author-email: chieh.t.wu@gmail.com
License: MIT
Keywords: ML,data analysis
Classifier: Development Status :: 3 - Alpha
Classifier: Intended Audience :: Developers
Classifier: Topic :: Software Development :: Build Tools
Classifier: License :: OSI Approved :: MIT License
Classifier: Programming Language :: Python :: 3.4
Classifier: Programming Language :: Python :: 3.5
Classifier: Programming Language :: Python :: 3.6
Classifier: Programming Language :: Python :: 3.7
